stockfighter/__init__.py
stockfighter/gm.py
stockfighter/stockfighter.py
stockfighter/storage.py
stockfighter-0.2.7.dist-info/DESCRIPTION.rst
stockfighter-0.2.7.dist-info/METADATA
stockfighter-0.2.7.dist-info/RECORD
stockfighter-0.2.7.dist-info/WHEEL
stockfighter-0.2.7.dist-info/metadata.json
stockfighter-0.2.7.dist-info/top_level.txt
