Metadata-Version: 2.0
Name: stockfighter
Version: 0.2.7
Summary: API wrapper for Stockfighter
Home-page: https://github.com/striglia/stockfighter
Author: Scott Triglia
Author-email: scott.triglia@gmail.com
License: ISCL
Keywords: stockfighter
Platform: UNKNOWN
Classifier: Development Status :: 2 - Pre-Alpha
Classifier: Intended Audience :: Developers
Classifier: License :: OSI Approved :: ISC License (ISCL)
Classifier: Natural Language :: English
Classifier: Programming Language :: Python :: 2
Classifier: Programming Language :: Python :: 2.6
Classifier: Programming Language :: Python :: 2.7
Classifier: Programming Language :: Python :: 3
Classifier: Programming Language :: Python :: 3.3
Classifier: Programming Language :: Python :: 3.4
Classifier: Programming Language :: Python :: 3.5
Requires-Dist: requests
Requires-Dist: six
